[
  {
    "id": 1754649301011,
    "workspaceId": 1,
    "date": "2025-08-08T10:35:01.008Z"
  },
  {
    "id": 1754649831842,
    "workspaceId": 2,
    "date": "2025-08-08T10:43:51.840Z"
  },
  {
    "id": 1754651927511,
    "workspaceId": 1,
    "date": "2025-08-08T11:18:47.509Z"
  },
  {
    "id": 1754653433032,
    "workspaceId": 3,
    "date": "2025-08-08T11:43:53.028Z"
  },
  {
    "id": 1754654172293,
    "workspaceId": 1,
    "date": "2025-08-08T11:56:12.291Z",
    "userEmail": "test@gmail.com"
  },
  {
    "id": 1754654575639,
    "workspaceId": 1,
    "date": "2025-08-08T12:02:55.637Z",
    "userEmail": "test@gmail.com"
  },
  {
    "id": 1754654689923,
    "workspaceId": 1,
    "date": "2025-08-08T12:04:49.922Z",
    "userEmail": "test@gmail.com"
  },
  {
    "id": 1754654948560,
    "workspaceId": 1,
    "date": "2025-08-08T12:09:08.558Z",
    "userEmail": "Hello456@gmail.com"
  },
  {
    "id": 1754693729868,
    "workspaceId": 1,
    "date": "2025-08-08T22:55:29.847Z",
    "userEmail": "Hello456@gmail.com"
  }
]